opap/__init__.py
opap-1.0.2.dist-info/LICENSE
opap-1.0.2.dist-info/METADATA
opap-1.0.2.dist-info/WHEEL
opap-1.0.2.dist-info/top_level.txt
opap-1.0.2.dist-info/RECORD
