Metadata-Version: 2.1
Name: opap
Version: 1.0.2
Summary: An api that collects data from opap.
Home-page: https://github.com/George-Kaloudis/opap
Author: George Kaloudis
Author-email: georgekal123@gmail.com
License: UNKNOWN
Platform: UNKNOWN
Classifier: Programming Language :: Python :: 3
Classifier: License :: OSI Approved :: MIT License
Classifier: Operating System :: OS Independent
